README.rst
setup.py
workertier/__init__.py
workertier/cli.py
workertier/config.py
workertier/consumer.py
workertier/handler.py
workertier/version.py
workertier.egg-info/PKG-INFO
workertier.egg-info/SOURCES.txt
workertier.egg-info/dependency_links.txt
workertier.egg-info/entry_points.txt
workertier.egg-info/not-zip-safe
workertier.egg-info/requires.txt
workertier.egg-info/top_level.txt
workertier/backends/__init__.py
workertier/backends/cache/__init__.py
workertier/backends/cache/memcached.py
workertier/backends/cache/memory.py
workertier/backends/cache/memcluster/__init__.py
workertier/backends/cache/memcluster/dns.py
workertier/backends/cache/memcluster/scalr.py
workertier/backends/dispatcher/__init__.py
workertier/backends/dispatcher/memory.py
workertier/backends/dispatcher/rabbitmq.py
workertier/backends/dispatcher/dynrabbit/__init__.py
workertier/backends/dispatcher/dynrabbit/backoff.py
workertier/backends/dispatcher/dynrabbit/scalr.py
workertier/backends/pool/__init__.py
workertier/backends/pool/connection.py
workertier/backends/pool/pool.py
workertier/backends/remote/__init__.py
workertier/backends/remote/base.py
workertier/backends/remote/dns.py
workertier/backends/remote/scalr.py
workertier/tests/__init__.py
workertier/tests/test_connection_pool.py
workertier/tests/test_consumer.py
workertier/tests/test_dynrabbit.py
workertier/tests/test_handler.py
workertier/tests/test_memcached.py
workertier/tests/test_memcluster.py
workertier/tests/test_rabbit.py
workertier/tests/test_remote.py
workertier/tests/test_signal_handler.py
workertier/utils/__init__.py
workertier/utils/signal_handler.py