Metadata-Version: 1.0
Name: workertier
Version: 0.5.0
Summary: A Scalr tutorial: Web frontend + Memcached + RabbitMQ
Home-page: https://github.com/scalr/tutorial-workertier
Author: Thomas Orozco
Author-email: thomas@scalr.com
License: Apache 2
Platform: UNKNOWN
Classifier: Development Status :: 2 - Pre-Alpha
Classifier: Intended Audience :: Developers
Classifier: License :: OSI Approved :: Apache Software License
Classifier: Natural Language :: English
Classifier: Programming Language :: Python :: 2
Classifier: Programming Language :: Python :: 2.7
